<?xml version="1.0" encoding="utf-8" ?>
<dwsync>
<file name="main.js" server="2dsandbox.legynds.com//" local="130651561251319632" remote="130651741200000000" />
<file name="bu4-main.js" server="2dsandbox.legynds.com//" local="130634999096183893" remote="130635179400000000" />
<file name="character-template.js" server="2dsandbox.legynds.com//" local="130649641354428817" remote="130649821800000000" />
<file name="FileSaver.min.js" server="2dsandbox.legynds.com//" local="130642098643119546" remote="130642279200000000" />
<file name="inv-templates.js" server="2dsandbox.legynds.com//" local="130651558444659100" remote="130651738200000000" />
<file name="handlebars.min.js" server="2dsandbox.legynds.com//" local="130646224116204569" remote="130646404200000000" />
<file name="inv-templates.js" server="ftp.legynds.com//seconddawn/" local="130653235200109312" remote="130653415200000000" />
<file name="main.js" server="ftp.legynds.com//seconddawn/" local="130653212897383669" remote="130653392400000000" />
</dwsync>